ninjavis.py
ninjavis-0.2.1.dist-info/entry_points.txt
ninjavis-0.2.1.dist-info/LICENSE
ninjavis-0.2.1.dist-info/WHEEL
ninjavis-0.2.1.dist-info/METADATA
ninjavis-0.2.1.dist-info/RECORD
