Metadata-Version: 2.1
Name: ninjavis
Version: 0.2.1
Summary: Generate visualization from Ninja build logs.
Home-page: https://github.com/chagui/ninjavis
License: MIT
Author: Guilhem Charles
Requires-Python: >=3.6,<4.0
Classifier: License :: OSI Approved :: MIT License
Classifier: Programming Language :: Python :: 3
Classifier: Programming Language :: Python :: 3.6
Classifier: Programming Language :: Python :: 3.7
Classifier: Programming Language :: Python :: 3.8
Classifier: Programming Language :: Python :: 3.9
Project-URL: Repository, https://github.com/chagui/ninjavis
